Metadata-Version: 2.1
Name: flask_template
Version: 0.4.4
Summary: Flask Project Template
Home-page: https://github.com/
Author: YIMIAN INC.
Author-email: zhangjinjie@yimian.com.cn
License: MIT
Keywords: flask development
Platform: UNKNOWN
Classifier: Development Status :: 3 - Alpha
Classifier: Intended Audience :: Developers
Classifier: Topic :: Software Development :: Build Tools
Classifier: License :: OSI Approved :: MIT License
Classifier: Programming Language :: Python :: 3
Classifier: Programming Language :: Python :: 3.3
Classifier: Programming Language :: Python :: 3.4
Classifier: Programming Language :: Python :: 3.5
Classifier: Programming Language :: Python :: 3.6
Requires-Python: >=3
Provides-Extra: dev
Provides-Extra: test
